ttscna/__init__.py
ttscna/ttscna.py
ttscna/tests/test_ttscna.py
ttscna-0.0.2.dist-info/LICENSE.txt
ttscna-0.0.2.dist-info/METADATA
ttscna-0.0.2.dist-info/WHEEL
ttscna-0.0.2.dist-info/top_level.txt
ttscna-0.0.2.dist-info/RECORD
